PaMSClient/PaMSClient.py
PaMSClient/__init__.py
PaMSClient-0.0.1.dist-info/METADATA
PaMSClient-0.0.1.dist-info/WHEEL
PaMSClient-0.0.1.dist-info/top_level.txt
PaMSClient-0.0.1.dist-info/RECORD
